{
  "project_info": {
    "project_number": "1020052408808",
    "project_id": "parcial-final-b5832",
    "storage_bucket": "parcial-final-b5832.firebasestorage.app"
  },
  "client": [
    {
      "client_info": {
        "mobilesdk_app_id": "1:1020052408808:android:b3c3e597dc0b75f0bc3c5d",
        "android_client_info": {
          "package_name": "com.example.parcial02"
        }
      },
      "oauth_client": [],
      "api_key": [
        {
          "current_key": "AIzaSyDa_zjX8FRGoIrWa_ySeieAW4CxNhHWlqo"
        }
      ],
      "services": {
        "appinvite_service": {
          "other_platform_oauth_client": []
        }
      }
    }
  ],
  "configuration_version": "1"
}